LICENSE
README.md
setup.py
singlefile_storage/__init__.py
singlefile_storage/__main__.py
singlefile_storage/help.py
singlefile_storage/storage.py
singlefile_storage.egg-info/PKG-INFO
singlefile_storage.egg-info/SOURCES.txt
singlefile_storage.egg-info/dependency_links.txt
singlefile_storage.egg-info/entry_points.txt
singlefile_storage.egg-info/requires.txt
singlefile_storage.egg-info/top_level.txt
singlefile_storage/static/logo.svg
singlefile_storage/static/robots.txt
singlefile_storage/templates/content.html
singlefile_storage/templates/login.html