Metadata-Version: 2.4
Name: singlefile-storage
Version: 1.0.12
Summary: SingleFile Rest Storage for python.
Home-page: https://github.com/qicongsheng/singlefile-storage
Author: qicongsheng
Author-email: qicongsheng@outlook.com
License: MIT License
Keywords: singlefile-storage
Platform: any
License-File: LICENSE
Requires-Dist: flask
Requires-Dist: flask_httpauth
Dynamic: author
Dynamic: author-email
Dynamic: home-page
Dynamic: keywords
Dynamic: license
Dynamic: license-file
Dynamic: platform
Dynamic: requires-dist
Dynamic: summary
